fastapi-query-parameter-model/__init__.py
fastapi-query-parameter-model/query_parameter_model.py
fastapi_query_parameter_model/__init__.py
fastapi_query_parameter_model/query_parameter_model.py
fastapi_query_parameter_model-0.1.2.dist-info/METADATA
fastapi_query_parameter_model-0.1.2.dist-info/WHEEL
fastapi_query_parameter_model-0.1.2.dist-info/top_level.txt
fastapi_query_parameter_model-0.1.2.dist-info/RECORD
