Metadata-Version: 2.1
Name: fastapi-query-parameter-model
Version: 0.1.2
Summary: A powerful and easy-to-use model for converting camelCase query parameters into snake_case parameters of an object
Home-page: https://github.com/PierroD/fastapi-query-parameter-model
Author: Pierre DUVEAU
Author-email: pierre@duveau.org
Classifier: Development Status :: 3 - Alpha
Classifier: Intended Audience :: Developers
Classifier: License :: OSI Approved :: MIT License
Classifier: Programming Language :: Python :: 3
Classifier: Programming Language :: Python :: 3.8
Classifier: Programming Language :: Python :: 3.9
Classifier: Programming Language :: Python :: 3.10
Classifier: Programming Language :: Python :: 3.11
Classifier: Programming Language :: Python :: 3.12
Classifier: Topic :: Software Development :: Libraries :: Python Modules
Requires-Python: >=3.6
Requires-Dist: fastapi
Requires-Dist: pydantic
